COPYING.SPL.txt
README.txt
ez_setup.py
setup.py
darcsver-1.7.0.egg/EGG-INFO/PKG-INFO
darcsver-1.7.0.egg/EGG-INFO/SOURCES.txt
darcsver-1.7.0.egg/EGG-INFO/dependency_links.txt
darcsver-1.7.0.egg/EGG-INFO/entry_points.txt
darcsver-1.7.0.egg/EGG-INFO/not-zip-safe
darcsver-1.7.0.egg/EGG-INFO/top_level.txt
darcsver-1.7.0.egg/darcsver/__init__.py
darcsver-1.7.0.egg/darcsver/_version.py
darcsver-1.7.0.egg/darcsver/darcsvermodule.py
darcsver-1.7.0.egg/darcsver/setuptools_command.py
darcsver-1.7.0.egg/darcsver/test/__init__.py
darcsver-1.7.0.egg/darcsver/test/test_darcsver.py
darcsver-1.7.0.egg/scripts/__init__.py
darcsver-1.7.0.egg/scripts/darcsverscript.py
darcsver-1.7.0.egg/share/doc/python-darcsver/README.txt
zbase62/__init__.py
zbase62/_version.py
zbase62/zbase62.py
zbase62.egg-info/PKG-INFO
zbase62.egg-info/SOURCES.txt
zbase62.egg-info/dependency_links.txt
zbase62.egg-info/not-zip-safe
zbase62.egg-info/top_level.txt
zbase62/test/__init__.py
zbase62/test/test_base62.py